README.md
setup.py
src/cubicle/AST.py
src/cubicle/__init__.py
src/cubicle/compiler.py
src/cubicle/core.md
src/cubicle/dynamic.py
src/cubicle/formulae.py
src/cubicle/frontend.py
src/cubicle/middle.py
src/cubicle/runtime.py
src/cubicle/static.py
src/cubicle/utility.py
src/cubicle/veneer.py
src/cubicle/version.py
src/cubicle/xl_schema.py
src/cubicle.egg-info/PKG-INFO
src/cubicle.egg-info/SOURCES.txt
src/cubicle.egg-info/dependency_links.txt
src/cubicle.egg-info/requires.txt
src/cubicle.egg-info/top_level.txt