Metadata-Version: 2.1
Name: cubicle
Version: 0.8.11
Summary: a high-level declarative domain-specific language for high-functioning, professional-looking, business-oriented numerical and graphical reporting
Home-page: https://github.com/kjosib/glowing-chainsaw
Author: Ian Kjos
Author-email: kjosib@gmail.com
License: MIT
Platform: UNKNOWN
Classifier: Programming Language :: Python :: 3
Classifier: License :: OSI Approved :: MIT License
Classifier: Operating System :: OS Independent
Classifier: Development Status :: 3 - Alpha
Classifier: Intended Audience :: Developers
Classifier: Topic :: Office/Business
Classifier: Topic :: Software Development :: Interpreters
Classifier: Topic :: Software Development :: Libraries
Requires-Python: >=3.7
